nerdlerxml
