Metadata-Version: 2.1
Name: nerdlerxml
Version: 1.0.1
Summary: Converts XML to a dictionary. Can take inputs from URL, a file and binary data
Home-page: https://github.com/nerdlertech/nerdlerxml
Author: Hendrik Koester
License-File: LICENSE
